.darglint
.flake8
.gitignore
.pre-commit-config.yaml
.prettierignore
.yamllint.yaml
LICENSE
README.md
cspell.config.yaml
mypy.ini
pyproject.toml
setup.cfg
.config/dictionary.txt
.github/workflows/collection.yml
images/vscode_debug.png
images/vscode_overview.png
src/pytest_ansible_units/__init__.py
src/pytest_ansible_units/_version.py
src/pytest_ansible_units.egg-info/PKG-INFO
src/pytest_ansible_units.egg-info/SOURCES.txt
src/pytest_ansible_units.egg-info/dependency_links.txt
src/pytest_ansible_units.egg-info/entry_points.txt
src/pytest_ansible_units.egg-info/requires.txt
src/pytest_ansible_units.egg-info/top_level.txt