Metadata-Version: 2.1
Name: pytest-ansible-units
Version: 0.1.dev50
Summary: A pytest plugin for running unit tests within an ansible collection
Home-page: https://github.com/cidrblock/pytest-ansible-units
Author: Bradley A. Thornton
Author-email: bthornto@redhat.com
License: GNU GPL v3.0
Platform: UNKNOWN
Classifier: Framework :: Pytest
Classifier: Intended Audience :: Developers
Classifier: License :: OSI Approved :: GNU General Public License v3 (GPLv3)
Classifier: Operating System :: OS Independent
Classifier: Programming Language :: Python :: 3
Classifier: Programming Language :: Python :: 3 :: Only
Classifier: Programming Language :: Python :: 3.8
Classifier: Programming Language :: Python :: 3.9
Classifier: Programming Language :: Python :: 3.10
Classifier: Programming Language :: Python :: Implementation :: CPython
Classifier: Programming Language :: Python :: Implementation :: PyPy
Classifier: Topic :: Software Development :: Testing
Requires-Python: >=3.8
Provides-Extra: ansible
Provides-Extra: ansible-base
Provides-Extra: ansible-core
Provides-Extra: test
License-File: LICENSE
